{"id":"d260f10f-139a-4b1e-9a68-a8ccdcca1b0b","timestamp":1748001708624,"matcher":{"static":{},"wildcard":{},"dynamic":{}},"prerendered":["/","/museum","/atelier","/show","/schedule","/access","/alignment","/data","/en","/en/alignment","/en/access","/atelier/box","/atelier/lightcop","/atelier/pendulum","/en/atelier","/en/atelier/pendulum","/en/data","/en/atelier/box","/en/atelier/lightcop","/en/finder","/en/format","/finder","/en/kimiS/1_2","/format","/kimiS","/en/kimiS/1_1","/en/kimiS/2_1","/museum/heat","/museum/clothes","/kimiS/1_1","/kimiS/1_2","/kimiS/2_1","/kimiS/2_2","/en/kimiS/2_2","/en/kimiS","/en/museum","/en/schedule","/en/show","/en/naruhodojikkan","/en/museum/heat","/en/museum/clothes","/en/museum/pen","/en/show/rotation","/museum/pen","/naruhodojikkan","/show/rotation"]}